codeinkit/__init__.py
codeinkit/flows.py
codeinkit-0.0.1.dist-info/LICENSE
codeinkit-0.0.1.dist-info/METADATA
codeinkit-0.0.1.dist-info/WHEEL
codeinkit-0.0.1.dist-info/top_level.txt
codeinkit-0.0.1.dist-info/RECORD
