Metadata-Version: 2.1
Name: codeinkit
Version: 0.0.1
Summary: UNKNOWN
Home-page: https://github.com/codeinkit/pyflows
Author: codeinkit
Author-email: info@codeinkit.com
License: UNKNOWN
Platform: UNKNOWN
Classifier: Programming Language :: Python :: 3
Classifier: License :: OSI Approved :: MIT License
Classifier: Operating System :: OS Independent
Requires-Python: >=3.6
